python_cronet.libs/libuuid-95b83d40.so.1.3.0
python_cronet.libs/libunistring-05abdd40.so.2.1.0
python_cronet.libs/libcronet-1a047a4e.133.0.6943.98.so
python_cronet.libs/libgobject-2-e8d4ed32.0.so.0.5600.4
python_cronet.libs/libgio-2-52cdeaca.0.so.0.5600.4
python_cronet.libs/libplds4-c96adacf.so
python_cronet.libs/libgmodule-2-72c85b95.0.so.0.5600.4
python_cronet.libs/libnettle-37944285.so.6.5
python_cronet.libs/libnspr4-50db7ede.so
python_cronet.libs/libp11-kit-ac9dcd7e.so.0.3.0
python_cronet.libs/libselinux-7e3eb199.so.1
python_cronet.libs/libidn2-2f4a5893.so.0.3.6
python_cronet.libs/libpcre-0dd207b5.so.1.2.10
python_cronet.libs/libffi-3a37023a.so.6.0.2
python_cronet.libs/libnssutil3-6f5c6901.so
python_cronet.libs/libgnutls-5ac79744.so.30.28.2
python_cronet.libs/libgmp-d944b113.so.10.3.2
python_cronet.libs/libplc4-5da7697c.so
python_cronet.libs/libblkid-a9167753.so.1.1.0
python_cronet.libs/libglib-2-450f46b8.0.so.0.5600.4
python_cronet.libs/libtasn1-222cca92.so.6.5.5
python_cronet.libs/libnss3-97de30de.so
python_cronet.libs/libhogweed-cd4c53be.so.4.5
python_cronet.libs/libmount-ec61bd71.so.1.1.0
python_cronet.libs/libpcre2-8-516f4c9d.so.0.7.1
cronet/_cronet.cpython-38-x86_64-linux-gnu.so
cronet/_cronet.c
cronet/__init__.py
cronet/cronet.py
python_cronet-0.1.6.dist-info/LICENSE
python_cronet-0.1.6.dist-info/WHEEL
python_cronet-0.1.6.dist-info/METADATA
python_cronet-0.1.6.dist-info/top_level.txt
python_cronet-0.1.6.dist-info/RECORD
