Metadata-Version: 2.1
Name: python-cronet
Version: 0.1.6
Summary: Python wrapper for Chromium's http library
Author: Lucas Moauro
Project-URL: Homepage, https://github.com/lagenar/python-cronet
Project-URL: Issues, https://github.com/lagenar/python-cronet/issues
Classifier: Programming Language :: Python :: 3
Classifier: License :: OSI Approved :: MIT License
Classifier: Operating System :: OS Independent
Requires-Python: >=3.8
License-File: LICENSE
Requires-Dist: multidict
Provides-Extra: test
Requires-Dist: pytest; extra == "test"
Requires-Dist: aiohttp; extra == "test"
Requires-Dist: pytest-asyncio; extra == "test"
